cnn_methods/__init__.py
cnn_methods/classification_nn.py
cnn_methods/utils.py
cnn_methods/yolo_sam.py
cnn_methods/images/apple.jpg
cnn_methods/images/banana.jpg
cnn_methods/images/coches.jpg
cnn_methods/images/orange.png
cnn_methods/images/rottenapple.jpg
cnn_methods/images/rottenbanana.png
cnn_methods/images/rottenorange.jpg
cnn_methods/images/yolov5-model-structure.avif
cnn_methods-1.2.0.dist-info/METADATA
cnn_methods-1.2.0.dist-info/WHEEL
cnn_methods-1.2.0.dist-info/licenses/LICENSE
cnn_methods-1.2.0.dist-info/RECORD
