Metadata-Version: 2.4
Name: cnn-methods
Version: 1.2.0
Summary: Deep learning project for object classification, detection and classification using YOLO and SAM
Author-email: Emilio Rodrigo Carreira Villalta <emiliorodrigo.ecr@gmail.com>
Maintainer-email: Emilio Rodrigo Carreira Villalta <emiliorodrigo.ecr@gmail.com>
License-File: LICENSE
Classifier: Development Status :: 5 - Production/Stable
Classifier: Intended Audience :: Science/Research
Classifier: License :: OSI Approved :: GNU General Public License v3 (GPLv3)
Classifier: Programming Language :: Python :: 3.10
Classifier: Topic :: Scientific/Engineering :: Artificial Intelligence
Requires-Python: >=3.8
Requires-Dist: gdown
Requires-Dist: graphviz
Requires-Dist: matplotlib
Requires-Dist: pandas
Requires-Dist: sphinx-rtd-theme==3.0.2
Requires-Dist: sphinx==8.1.3
Requires-Dist: torch; sys_platform != 'win32'
Requires-Dist: torchvision; sys_platform != 'win32'
Requires-Dist: triton; sys_platform != 'win32'
Requires-Dist: ultralytics
